nepali_unicoder/__init__.py
nepali_unicoder/__main__.py
nepali_unicoder/convert.py
nepali_unicoder/engine.py
nepali_unicoder/loader.py
nepali_unicoder/rules.py
nepali_unicoder/tokenizer.py
nepali_unicoder/trie.py
nepali_unicoder/word_maps.json
nepali_unicoder-0.1.2.dist-info/licenses/LICENSE
nepali_unicoder-0.1.2.dist-info/METADATA
nepali_unicoder-0.1.2.dist-info/WHEEL
nepali_unicoder-0.1.2.dist-info/top_level.txt
nepali_unicoder-0.1.2.dist-info/RECORD
