Metadata-Version: 2.4
Name: nepali_unicoder
Version: 0.1.2
Summary: A Python package for Roman to Nepali (Devanagari) transliteration
Author-email: realsanjeev <075bei033.sanjeev@pcampus.edu.np>
License-Expression: MIT
Project-URL: Homepage, https://github.com/realsanjeev/nepali_unicoder
Project-URL: Documentation, https://realsanjeev.github.io/nepali_unicoder/
Project-URL: Bug Tracker, https://github.com/realsanjeev/nepali_unicoder/issues
Keywords: nepali,unicoder,roman to devanagari,nepali transliteration,preeti to unicode
Classifier: Programming Language :: Python
Classifier: Programming Language :: Python :: 3
Classifier: Operating System :: OS Independent
Requires-Python: >=3.7
License-File: LICENSE
Provides-Extra: dev
Requires-Dist: pre-commit; extra == "dev"
Requires-Dist: mkdocs; extra == "dev"
Requires-Dist: mkdocs-material; extra == "dev"
Dynamic: license-file
